viewcsv/__init__.py
viewcsv/cli.py
viewcsv/count_cjk.py
viewcsv-1.1.1.dist-info/LICENSE
viewcsv-1.1.1.dist-info/METADATA
viewcsv-1.1.1.dist-info/WHEEL
viewcsv-1.1.1.dist-info/entry_points.txt
viewcsv-1.1.1.dist-info/top_level.txt
viewcsv-1.1.1.dist-info/RECORD
