Metadata-Version: 2.1
Name: viewcsv
Version: 1.1.1
Summary: A command-line tool for viewing CSV files with aligned columns
Author-email: Jiamin Lin <jiamin2001g@gmail.com>
License: GNU GENERAL PUBLIC LICENSE
Project-URL: Homepage, https://github.com/Jaimin1304/view-csv
Project-URL: Repository, https://github.com/Jaimin1304/view-csv.git
Project-URL: Bug Tracker, https://github.com/Jaimin1304/view-csv/issues
Keywords: csv,cli,viewer,terminal,console
Classifier: Development Status :: 5 - Production/Stable
Classifier: Environment :: Console
Classifier: Intended Audience :: Developers
Classifier: License :: OSI Approved :: GNU General Public License v3 (GPLv3)
Classifier: Operating System :: OS Independent
Classifier: Programming Language :: Python :: 3
Classifier: Programming Language :: Python :: 3.7
Classifier: Programming Language :: Python :: 3.8
Classifier: Programming Language :: Python :: 3.9
Classifier: Programming Language :: Python :: 3.10
Classifier: Programming Language :: Python :: 3.11
Classifier: Programming Language :: Python :: 3.12
Classifier: Topic :: Text Processing :: General
Classifier: Topic :: Utilities
Requires-Python: >=3.7
License-File: LICENSE
Requires-Dist: grapheme
